confu/__init__.py
confu/cli.py
confu/config.py
confu/exceptions.py
confu/generator.py
confu/schema/__init__.py
confu/schema/core.py
confu/schema/inet.py
confu/util.py
confu-1.8.0.dist-info/LICENSE
confu-1.8.0.dist-info/WHEEL
confu-1.8.0.dist-info/METADATA
confu-1.8.0.dist-info/RECORD
